{
  "host": "10.5.99.10",
  "status": 599,
  "response": {
    "error": "HTTPConnectionPool(host='10.5.99.10', port=8000): Read timed out. (read timeout=90)",
    "url": "http://10.5.99.10:8000/start_experiments_consumer",
    "payload": {
      "requirements": "zero_packet_loss",
      "offers_to_wait": 2,
      "meo_endpoint": "http://10.5.99.10:6666",
      "ip_address": "10.5.99.10",
      "vxlan_interface": "ens3",
      "node_id": 10,
      "export_to_csv": true,
      "csv_path": "/experiments/multiple-offers/clique/20-mecs/consumer_10_run_2.csv"
    }
  }
}